terminalutils/__init__.py
terminalutils/main.py
terminalutils-0.0.1.dist-info/LICENSE
terminalutils-0.0.1.dist-info/METADATA
terminalutils-0.0.1.dist-info/WHEEL
terminalutils-0.0.1.dist-info/top_level.txt
terminalutils-0.0.1.dist-info/RECORD
