Metadata-Version: 2.1
Name: terminalutils
Version: 0.0.1
Summary: A set of terminal utilities for Python command line based applications
Home-page: https://github.com/pypa/sampleproject
Author: JustAnotherProgrammer
License: UNKNOWN
Project-URL: GitHub, https://github.com/JustAnother-Programmer/terminalutils
Project-URL: Bug Tracker, https://github.com/JustAnother-Programmer/terminalutils/issues
Platform: UNKNOWN
Classifier: Programming Language :: Python :: 3
Classifier: License :: OSI Approved :: MIT License
Classifier: Operating System :: OS Independent
Requires-Python: >=3.6
License-File: LICENSE
